bitranox_template_cli_app_config_log_mail/__init__.py
bitranox_template_cli_app_config_log_mail/__init__conf__.py
bitranox_template_cli_app_config_log_mail/__main__.py
bitranox_template_cli_app_config_log_mail/behaviors.py
bitranox_template_cli_app_config_log_mail/cli.py
bitranox_template_cli_app_config_log_mail/config.py
bitranox_template_cli_app_config_log_mail/config_deploy.py
bitranox_template_cli_app_config_log_mail/config_show.py
bitranox_template_cli_app_config_log_mail/defaultconfig.toml
bitranox_template_cli_app_config_log_mail/enums.py
bitranox_template_cli_app_config_log_mail/logging_setup.py
bitranox_template_cli_app_config_log_mail/mail.py
bitranox_template_cli_app_config_log_mail/py.typed
bitranox_template_cli_app_config_log_mail/defaultconfig.d/10-logging.toml
bitranox_template_cli_app_config_log_mail/defaultconfig.d/20-mail.toml
bitranox_template_cli_app_config_log_mail-0.2.4.dist-info/METADATA
bitranox_template_cli_app_config_log_mail-0.2.4.dist-info/WHEEL
bitranox_template_cli_app_config_log_mail-0.2.4.dist-info/entry_points.txt
bitranox_template_cli_app_config_log_mail-0.2.4.dist-info/licenses/LICENSE
bitranox_template_cli_app_config_log_mail-0.2.4.dist-info/RECORD
