Metadata-Version: 2.4
Name: bitranox_template_cli_app_config_log_mail
Version: 0.2.4
Summary: Template CLI application with configuration management and structured logging
Project-URL: Homepage, https://github.com/bitranox/bitranox_template_cli_app_config_log_mail
Project-URL: Repository, https://github.com/bitranox/bitranox_template_cli_app_config_log_mail.git
Project-URL: Issues, https://github.com/bitranox/bitranox_template_cli_app_config_log_mail/issues
Author-email: bitranox <bitranox@gmail.com>
License: MIT
License-File: LICENSE
Keywords: cli,config,layered-config,logging,rich-click,template
Classifier: Environment :: Console
Classifier: License :: OSI Approved :: MIT License
Classifier: Operating System :: OS Independent
Classifier: Programming Language :: Python :: 3
Classifier: Programming Language :: Python :: 3 :: Only
Classifier: Programming Language :: Python :: 3.10
Classifier: Programming Language :: Python :: 3.11
Classifier: Programming Language :: Python :: 3.12
Classifier: Programming Language :: Python :: 3.13
Classifier: Typing :: Typed
Requires-Python: >=3.10
Requires-Dist: btx-lib-mail>=1.0.3
Requires-Dist: lib-cli-exit-tools>=2.2.3
Requires-Dist: lib-layered-config>=5.1.0
Requires-Dist: lib-log-rich>=6.0.0
Requires-Dist: rich-click>=1.9.5
Provides-Extra: dev
Requires-Dist: bandit>=1.9.2; extra == 'dev'
Requires-Dist: build>=1.3.0; extra == 'dev'
Requires-Dist: codecov-cli>=11.2.6; extra == 'dev'
Requires-Dist: import-linter>=2.9; extra == 'dev'
Requires-Dist: pip-audit>=2.10.0; extra == 'dev'
Requires-Dist: pyright>=1.1.407; extra == 'dev'
Requires-Dist: pytest-cov>=7.0.0; extra == 'dev'
Requires-Dist: pytest>=9.0.2; extra == 'dev'
Requires-Dist: rtoml>=0.13.0; extra == 'dev'
Requires-Dist: ruff>=0.14.10; extra == 'dev'
Requires-Dist: textual>=6.11.0; extra == 'dev'
Requires-Dist: twine>=6.2.0; extra == 'dev'
